rest_framework_requests/__init__.py
rest_framework_requests/api_docs.py
rest_framework_requests/api_endpoint.py
rest_framework_requests/compat.py
rest_framework_requests/settings.py
rest_framework_requests/urls.py
rest_framework_requests/views.py
rest_framework_requests/static/webpack.config.js
rest_framework_requests/static/webpack.rel.config.js
rest_framework_requests/static/rest_framework_requests/js/index.js
rest_framework_requests/static/rest_framework_requests/js/components/liveapi.js
rest_framework_requests/static/rest_framework_requests/js/components/request.js
rest_framework_requests/static/rest_framework_requests/js/components/response.js
rest_framework_requests/static/rest_framework_requests/js/components/fields/boolean.js
rest_framework_requests/static/rest_framework_requests/js/components/fields/text.js
rest_framework_requests/static/rest_framework_requests/js/components/helpers/header.js
rest_framework_requests/static/rest_framework_requests/js/components/request/add-fields.js
rest_framework_requests/static/rest_framework_requests/js/components/request/data.js
rest_framework_requests/static/rest_framework_requests/js/components/request/field-url.js
rest_framework_requests/static/rest_framework_requests/js/components/request/headers.js
rest_framework_requests/static/rest_framework_requests/js/components/request/methods.js
rest_framework_requests/static/rest_framework_requests/js/utils/jsonpp.js
rest_framework_requests/static/rest_framework_requests/js/utils/request.js
rest_framework_requests/static/rest_framework_requests/less/style.less
rest_framework_requests/templates/rest_framework_requests/base.html
rest_framework_requests/templates/rest_framework_requests/docs.html
rest_framework_requests/templates/rest_framework_requests/home.html
rest_framework_requests/templates/rest_framework_requests/components/fields_list.html
rest_framework_requests/templatetags/__init__.py
rest_framework_requests/templatetags/drfdocs_filters.py
drfrequests-0.5.dist-info/LICENSE
drfrequests-0.5.dist-info/METADATA
drfrequests-0.5.dist-info/WHEEL
drfrequests-0.5.dist-info/top_level.txt
drfrequests-0.5.dist-info/RECORD
