Metadata-Version: 2.1
Name: drfrequests
Version: 0.5
Summary: Document Web APIs made with Django Rest Framework.
Home-page: https://github.com/suhailvs/drfrequests
Author: Suhail VS
Author-email: suhailvs@gmail.com
License: UNKNOWN
Project-URL: Bug Tracker, https://github.com/suhailvs/drfrequests/issues
Platform: UNKNOWN
Classifier: Programming Language :: Python :: 3
Classifier: Programming Language :: Python :: 3.8
Classifier: Programming Language :: Python :: 3.9
Classifier: License :: OSI Approved :: MIT License
Classifier: Operating System :: OS Independent
Requires-Python: >=3.6
License-File: LICENSE
